Metadata-Version: 2.4
Name: thepipe_api
Version: 1.7.1
Summary: Get clean data from tricky documents, powered by VLMs.
Home-page: https://github.com/emcf/thepipe
Author: Emmett McFarlane
Author-email: emmett@thepi.pe
Classifier: Programming Language :: Python :: 3
Classifier: License :: OSI Approved :: MIT License
Classifier: Operating System :: OS Independent
Requires-Python: >=3.9
License-File: LICENSE
Requires-Dist: beautifulsoup4>=4.12
Requires-Dist: markdownify==0.12.1
Requires-Dist: magika>=0.5.0
Requires-Dist: moviepy==1.0.3
Requires-Dist: numpy>=1.23
Requires-Dist: openai>=1.51.0
Requires-Dist: openpyxl>=3.1
Requires-Dist: pandas>=2.0
Requires-Dist: pillow>=9.4
Requires-Dist: playwright>=1.47.0
Requires-Dist: pydantic>=2.7
Requires-Dist: pymupdf4llm==0.0.21
Requires-Dist: PyMuPDF==1.25.5
Requires-Dist: python-docx>=1.1
Requires-Dist: python-dotenv>=1.0
Requires-Dist: python-pptx>=0.6
Requires-Dist: pytube>=15.0
Requires-Dist: requests>=2.31
Provides-Extra: audio
Requires-Dist: openai-whisper>=20231117; extra == "audio"
Provides-Extra: semantic
Requires-Dist: sentence-transformers>=2.2.2; extra == "semantic"
Provides-Extra: llama-index
Requires-Dist: llama-index<0.11,>=0.10.50; extra == "llama-index"
Provides-Extra: gpu
Requires-Dist: torch<2.6,>=2.5; extra == "gpu"
Requires-Dist: torchvision<0.21,>=0.20; extra == "gpu"
Requires-Dist: torchaudio<2.6,>=2.5; extra == "gpu"
Requires-Dist: sentence-transformers>=2.2.2; extra == "gpu"
Requires-Dist: openai-whisper>=20231117; extra == "gpu"
Provides-Extra: all
Requires-Dist: llama-index<0.11,>=0.10.50; extra == "all"
Requires-Dist: openai-whisper>=20231117; extra == "all"
Requires-Dist: sentence-transformers>=2.2.2; extra == "all"
Requires-Dist: torch<2.6,>=2.5; extra == "all"
Requires-Dist: torchaudio<2.6,>=2.5; extra == "all"
Requires-Dist: torchvision<0.21,>=0.20; extra == "all"
Dynamic: author
Dynamic: author-email
Dynamic: classifier
Dynamic: description
Dynamic: description-content-type
Dynamic: home-page
Dynamic: license-file
Dynamic: provides-extra
Dynamic: requires-dist
Dynamic: requires-python
Dynamic: summary
